[
  {
    "dom": "<input aria-autocomplete=\"both\" aria-describedby=\"searchnotification\" aria-haspopup=\"true\" autocomplete=\"off\" class=\"autocomplete default input-edit ui-autocomplete-input\" data-datatype=\"string\" data-provide=\"typeahead\" id=\"sf-search\" name=\"sf-search\" placeholder=\"search\" role=\"textbox\" title=\"search\" type=\"text\"/>",
    "feature": "sf search sf search text search",
    "id": "552-text-0",
    "pattern": "search",
    "topic": "search"
  },
  {
    "dom": "<input aria-required=\"true\" autocomplete=\"off\" class=\"loginuser loginboxinfo\" id=\"login-userid\" jqac=\"on\" name=\"idtoken1\" placeholder=\"user id\" spellcheck=\"false\" type=\"text\"/>",
    "feature": "user id login userid idtoken1 text user id",
    "id": "552-text-1",
    "pattern": "user",
    "topic": "username"
  },
  {
    "dom": "<input aria-labelledby=\"namecapturelabel\" class=\"ember-view ember-text-field\" id=\"namecapture\" type=\"text\"/>",
    "feature": "name namecapture text",
    "id": "552-text-2",
    "pattern": "unk",
    "topic": "unk"
  },
  {
    "dom": "<input aria-labelledby=\"birthdatelabel\" class=\"ember-view ember-text-field\" id=\"birthdate\" required=\"\" type=\"text\"/>",
    "feature": "mm dd yyyy date of birth mm dd yyyy birthdate text",
    "id": "552-text-3",
    "pattern": "birthdate",
    "topic": "dob"
  },
  {
    "dom": "<input aria-labelledby=\"residenceaddresscapturelabel\" class=\"ember-view ember-text-field\" id=\"residenceaddresscapture\" type=\"text\"/>",
    "feature": "residential address residenceaddresscapture text",
    "id": "552-text-4",
    "pattern": "address",
    "topic": "address_1"
  },
  {
    "dom": "<input aria-labelledby=\"emaillabel\" class=\"ember-view ember-text-field\" id=\"email\" required=\"\" type=\"text\"/>",
    "feature": "email address email text",
    "id": "552-text-5",
    "pattern": "email",
    "topic": "email"
  },
  {
    "dom": "<input aria-labelledby=\"phonenumberlabel\" class=\"ember-view ember-text-field\" id=\"phonenumber\" required=\"\" type=\"text\"/>",
    "feature": "phone number phonenumber text",
    "id": "552-text-6",
    "pattern": "phone",
    "topic": "phone"
  },
  {
    "dom": "<input aria-labelledby=\"incomeamountlabel\" class=\"ember-view ember-text-field\" id=\"incomeamount\" required=\"\" type=\"text\"/>",
    "feature": "income incomeamount text",
    "id": "552-text-7",
    "pattern": "income",
    "topic": "income"
  },
  {
    "dom": "<input aria-labelledby=\"monthlyexpenseslabel\" class=\"ember-view ember-text-field\" id=\"monthlyexpenses\" required=\"\" type=\"text\"/>",
    "feature": "monthly expenses monthlyexpenses text",
    "id": "552-text-8",
    "pattern": "expenses",
    "topic": "expenses"
  },
  {
    "dom": "<input aria-required=\"true\" autocomplete=\"off\" class=\"loginboxinfo\" id=\"login-pass\" jqac=\"on\" name=\"idtoken2\" placeholder=\"password\" type=\"password\"/>",
    "feature": "password save user id login pass idtoken2 password password",
    "id": "552-password-0",
    "pattern": "pass",
    "topic": "password"
  }
]